MANIFEST.in
README.rst
setup.py
django_templates_i18n.egg-info/PKG-INFO
django_templates_i18n.egg-info/SOURCES.txt
django_templates_i18n.egg-info/dependency_links.txt
django_templates_i18n.egg-info/requires.txt
django_templates_i18n.egg-info/top_level.txt
templates_i18n/__init__.py
templates_i18n/admin.py
templates_i18n/models.py
templates_i18n/translation.py