Metadata-Version: 1.1
Name: django-templates-i18n
Version: 0.1.0
Summary: Translatable templates
Home-page: https://github.com/PragmaticMates/django-templates-i18n
Author: Pragmatic Mates
Author-email: info@pragmaticmates.com
License: BSD License
Keywords: django templates translation i18n
Platform: UNKNOWN
Classifier: Programming Language :: Python
Classifier: Programming Language :: Python :: 2.5
Classifier: Programming Language :: Python :: 2.6
Classifier: Programming Language :: Python :: 2.7
Classifier: Operating System :: OS Independent
Classifier: Environment :: Web Environment
Classifier: Intended Audience :: Developers
Classifier: Framework :: Django
Classifier: License :: OSI Approved :: BSD License
Classifier: Development Status :: 3 - Alpha
